hyint/__init__.py
hyint/hyint.py
hyint/test.py
hyint-0.3.1.dist-info/METADATA
hyint-0.3.1.dist-info/WHEEL
hyint-0.3.1.dist-info/licenses/LICENSE
hyint-0.3.1.dist-info/RECORD
