Metadata-Version: 2.1
Name: hyint
Version: 0.3.1
Summary: Hybrid (Symbolic-Numeric) Integration Package (based on sympy)
Project-URL: Homepage, https://github.com/siravan/hyint
Project-URL: Bug Tracker, https://github.com/siravan/hyint/issues
Author-email: Shahriar Iravanian <siravan@svtsim.com>
License-File: LICENSE
Classifier: License :: OSI Approved :: BSD License
Classifier: Operating System :: OS Independent
Classifier: Programming Language :: Python :: 3
Requires-Python: >=3.8
